{
    "version": 1,
	"default_attributes": {
		"font_color": {
			"r": 239,
			"g": 237,
			"b": 235,
			"a": 255
		},
		"font_outline_color": {
			"r": 50,
			"g": 29,
			"b": 25,
			"a": 255
		},
		"font_highlight_color": {
			"r": 18,
			"g": 196,
			"b": 131,
			"a": 255
		},
		"font_highlight2_color": {
			"r": 64,
			"g": 192,
			"b": 255,
			"a": 255
		}
	},	
    "script_entries": {
        "tutorial8a": {
            "sign": [
				"$ ",
				"",
				"Tus PV está bajos como",
				"resultado de un envenenamiento.",
				"La Poción de Gran Curación",
				"te ayudará."
            ],
            "attributes": {
                "font": "fonts/pixelmix.ttf#16#2",
				"font_highlight_color": {
					"r": 255,
					"g": 64,
					"b": 64,
					"a": 255
					},				
                "horizontal_justify": "center",
                "vertical_justify": "center",
                "line_padding": 0,
                "top_padding": 0,
                "inline_img_adjust_x": 0,
                "word_highlights": [
					[],
					[],
					[3],
					[3]
				],
                "word_highlights2": [
					[],
					[],
					[1],
					[],
					[],
					[1]
				],
				"video": {
					"background_img": "data/scripts/video_frame_noalpha.png",
					"background_border": 8,
					"path": "data/scripts/tutorial8/extrahealing_mk.ogv",
					"x": 0,
					"y": 0,
					"w": 0,
					"h": 0
				}
            },
            "variables": [
				{
				"type": "image",
				"value": "*#items/images/spells/extrahealing.png",
				"sizex": 32,
				"sizey": 32
				}			
			]
        },
        "tutorial8a_gamepad": {
            "sign": [
				"$ ",
				"",
                "Your HP is low as",
				"a result of poisoning.",
                "The Potion of Extra Healing",
				"will help."
            ],
            "attributes": {
                "font": "fonts/pixelmix.ttf#16#2",
				"font_highlight_color": {
					"r": 255,
					"g": 64,
					"b": 64,
					"a": 255
					},				
                "horizontal_justify": "center",
                "vertical_justify": "center",
                "line_padding": 0,
                "top_padding": 0,
                "inline_img_adjust_x": 0,
                "word_highlights": [
					[],
					[],
					[3],
					[3]
				],
                "word_highlights2": [
					[],
					[],
					[1],
					[],
					[],
					[1]
				],
				"video": {
					"background_img": "data/scripts/video_frame_noalpha.png",
					"background_border": 8,
					"path": "data/scripts/tutorial8/extrahealing_gamepad.ogv",
					"x": 0,
					"y": 0,
					"w": 0,
					"h": 0
				}
            },
            "variables": [
				{
				"type": "image",
				"value": "*#items/images/spells/extrahealing.png",
				"sizex": 32,
				"sizey": 32
				}			
			]
        },		
        "tutorial8b": {
            "sign": [
				"Para mezclar pociones, usa el",
				"Alambique con$ , y luego",
				"selecciona dos pociones diferentes",
				"con$ .",
				"",
				"Luego selecciona el resultado",
				"de la casilla inferior",
				"con$ para elaborarla."
            ],
            "attributes": {
                "font": "fonts/pixelmix.ttf#16#2",
                "horizontal_justify": "center",
                "vertical_justify": "center",
                "line_padding": 0,
                "top_padding": 0,
                "inline_img_adjust_x": 0,
                "word_highlights": [
					[],
					[0,1,2],
					[],
					[1],
					[],
					[],
					[2,3],
					[2,3]
				],
                "word_highlights2": [
					[1,2]
				]
            },
            "variables": [
				{
					"type": "input_glyph",
					"value": "MenuRightClick"
				},
				{
					"type": "input_glyph",
					"value": "MenuRightClick"
				},				
				{
					"type": "input_glyph",
					"value": "MenuRightClick"
				}				
			]
        },
        "tutorial8b_gamepad": {
            "sign": [
				"Para mezclar pociones, usa el",
				"Alambique con$ , y luego",
				"selecciona dos pociones diferentes",
				"con$ .",
				"",
				"Luego selecciona el resultado",
				"de la casilla inferior",
				"con$ para elaborarla."
            ],
            "attributes": {
                "font": "fonts/pixelmix.ttf#16#2",
                "horizontal_justify": "center",
                "vertical_justify": "center",
                "line_padding": 0,
                "top_padding": 0,
                "inline_img_adjust_x": 0,
                "word_highlights": [
					[],
					[0,1,2],
					[],
					[1],
					[],
					[2],
					[],
					[2,3]
				],
                "word_highlights2": [
					[1,2]
				]
            },
            "variables": [
				{
					"type": "input_glyph",
					"value": "MenuConfirm"
				},
				{
					"type": "input_glyph",
					"value": "MenuConfirm"
				},				
				{
					"type": "input_glyph",
					"value": "MenuAlt2"
				}				
			]
        },		
        "tutorial8c": {
            "sign": [
				"Las pociones pueden ser",
				"valiosas ayudas para",
				"los aventureros, y",
				"poderosas armas",
				"contra sus enemigos.",
				"",
				"Quienes dominen su uso",
				"podrán conquistar la",
				"mazmorra."
            ],
            "attributes": {
                "font": "fonts/pixelmix.ttf#16#2",
                "horizontal_justify": "center",
                "vertical_justify": "center",
                "line_padding": 0,
                "top_padding": 0,
                "inline_img_adjust_x": 0,
                "word_highlights": [],
                "word_highlights2": [
					[],
					[0,1],
					[],
					[0,1]
				]
            },
            "variables": []
        },
        "tutorial8d": {
            "sign": [
				"Los alambiques benditos pueden",
				"producir brebajes benditos.",
				"$",
				"El agua y jugo benditos",
				"tienen un gran valor curativo."
            ],
            "attributes": {
                "font": "fonts/pixelmix.ttf#16#2",
                "horizontal_justify": "center",
                "vertical_justify": "center",
                "line_padding": 0,
                "top_padding": 0,
                "inline_img_adjust_x": 0,
                "word_highlights": [],
                "word_highlights2": [
					[0,1],
					[1,2],
					[],
					[],
					[2]
				]
            },
            "variables": [
				{
				"type": "image",
				"value": "*#data/scripts/tutorial8/sign_blessedalembic.png",
				"sizex": 0,
				"sizey": 0
				}			
			]
        },
        "tutorial8e": {
            "sign": [
				"Los alambiques malditos pueden",
				"producir brebajes malditos.",
				"$",
				"Esto los corrompe y",
				"pueden causar más daño.",
				"El Agua Maldita es capaz",
				"de maldecir un objeto."
            ],
            "attributes": {
                "font": "fonts/pixelmix.ttf#16#2",
				"font_highlight_color": {
					"r": 255,
					"g": 64,
					"b": 64,
					"a": 255
					},	
                "horizontal_justify": "center",
                "vertical_justify": "center",
                "line_padding": 0,
                "top_padding": 0,
                "inline_img_adjust_x": 0,
                "word_highlights": [
					[0,1],
					[],
					[],
					[],
					[],
					[0,1]
				],
                "word_highlights2": [
					[],
					[],
					[],
					[],
					[2,3]
				]
            },
            "variables": [
				{
				"type": "image",
				"value": "*#data/scripts/tutorial8/sign_cursedalembic.png",
				"sizex": 0,
				"sizey": 0
				}		
			]
        },
        "tutorial8f": {
            "sign": [
				"Debes usar lo que",
				"has aprendido, y",
				"tu suministro de pociones",
				"para tener éxito. Asegúrate de",
				"estar preparado.",
				"",
				"Ahora serás puesto a prueba.",
				"Purga el área de",
				"los no-muertos."
            ],
            "attributes": {
                "font": "fonts/pixelmix.ttf#16#2",
                "horizontal_justify": "center",
                "vertical_justify": "center",
                "line_padding": 0,
                "top_padding": 0,
                "inline_img_adjust_x": 0,
                "word_highlights": [],
                "word_highlights2": [
					[],
					[],
					[1,2,3]
				]
            },
            "variables": []
        },
        "tutorial8g": {
            "sign": [
				"Los alquimistas hábiles",
				"tienen mejores chances",
				"de duplicar con agua.",
				"",
				"El fracaso resultará en",
				"la pérdida de la poción."
            ],
            "attributes": {
                "font": "fonts/pixelmix.ttf#16#2",
				"font_highlight_color": {
					"r": 255,
					"g": 64,
					"b": 64,
					"a": 255
					},					
                "horizontal_justify": "center",
                "vertical_justify": "center",
                "line_padding": 0,
                "top_padding": 0,
                "inline_img_adjust_x": 0,
                "word_highlights": [
					[],
					[],
					[],
					[],
					[],
					[0,1,2,3]
				],
                "word_highlights2": [
					[0]
				]
            },
            "variables": []
        },		
        "tutorial8h": {
            "sign": [
				"Para ver las chances de duplicación,",
				"pasa el cursor sobre la casilla",
				"inferior del Alambique una vez",
				"que tu poción y el agua estén",
				"listos para la elaboración."
            ],
            "attributes": {
                "font": "fonts/pixelmix.ttf#16#2",
                "horizontal_justify": "center",
                "vertical_justify": "center",
                "line_padding": 0,
                "top_padding": 0,
                "inline_img_adjust_x": 0,
                "word_highlights": [
					[],
					[1],
					[],
					[],
					[0,1,2]
				],
                "word_highlights2": [
					[1]
				]
            },
            "variables": []
        },
        "tutorial8i": {
            "sign": [
				"Puedes mejorar tu",
				"Habilidad Alquímica",
				"bebiendo pociones por",
				"primera vez.",
				"",
				"$"
            ],
            "attributes": {
                "font": "fonts/pixelmix.ttf#16#2",
                "horizontal_justify": "center",
                "vertical_justify": "center",
                "line_padding": 0,
                "top_padding": 0,
                "inline_img_adjust_x": 0,
                "word_highlights": [],
                "word_highlights2": [
					[],
					[],
					[0,1]
				]
            },
            "variables": [
				{
				"type": "image",
				"value": "*#images/ui/SkillSheet/Icons/Alchemy02_32.png",
				"sizex": 32,
				"sizey": 32
				}				
			]
        },
        "tutorial8j": {
            "sign": [
				"Ante ti tienes el",
				"Alambique que puede ser",
				"usado para elaborar pociones.",
				"$",
				"Mezcla nuevas pociones desde",
				"dos botellas diferentes."
            ],
            "attributes": {
                "font": "fonts/pixelmix.ttf#16#2",
                "horizontal_justify": "center",
                "vertical_justify": "center",
                "line_padding": 0,
                "top_padding": 0,
                "inline_img_adjust_x": 0,
                "word_highlights": [],
                "word_highlights2": [
					[],
					[0],
					[],
					[],
					[],
					[0,1]
				]
            },
            "variables": [
				{
				"type": "image",
				"value": "*#data/scripts/tutorial8/sign_alembic.png",
				"sizex": 0,
				"sizey": 0
				}				
			]
        },
        "tutorial8k": {
            "sign": [
				"Cuidado con el enemigo mortal",
				"tras esta puerta.",
				"",
				"Sería sabio mantener",
				"esta puerta cerrada."
            ],
            "attributes": {
                "font": "fonts/pixelmix.ttf#16#2",
				"font_highlight_color": {
					"r": 255,
					"g": 64,
					"b": 64,
					"a": 255
					},					
                "horizontal_justify": "center",
                "vertical_justify": "center",
                "line_padding": 0,
                "top_padding": 0,
                "inline_img_adjust_x": 0,
                "word_highlights": [
					[2,3]
				],
                "word_highlights2": [
					[],
					[],
					[],
					[],
					[3]
				]
            },
            "variables": []
        },
        "tutorial8l": {
            "sign": [
				"La palanca de esta puerta",
				"se encuentra más allá de la",
				"araña en la otra habitación."
            ],
            "attributes": {
                "font": "fonts/pixelmix.ttf#16#2",
                "horizontal_justify": "center",
                "vertical_justify": "center",
                "line_padding": 0,
                "top_padding": 0,
                "inline_img_adjust_x": 0,
                "word_highlights": [],
                "word_highlights2": [
					[],
					[1,2,3]
				],
				"video": {
					"background_img": "data/scripts/video_frame_half_noalpha.png",
					"background_border": 8,
					"path": "data/scripts/tutorial8/spiderlever.ogv",
					"x": 0,
					"y": 0,
					"w": 0,
					"h": 0
				}
            },
            "variables": []
        },
        "tutorial8m": {
            "sign": [
				"Poción de Parálisis",
				"",
				"$ ",
				"",
				"Inflige Parálisis,",
				"deteniendo el movimiento y",
				"los ataques. Puedes beber",
				"pociones mientras estás bajo",
				"los efectos de parálisis."
            ],
            "attributes": {
                "font": "fonts/pixelmix.ttf#16#2",
                "horizontal_justify": "center",
                "vertical_justify": "center",
                "line_padding": 0,
                "top_padding": 0,
                "inline_img_adjust_x": 0,
                "word_highlights": [],
                "word_highlights2": [
					[],
					[],
					[],
					[],
					[],
					[0,1]
				]
            },
            "variables": [
				{
				"type": "image",
				"value": "*#images/ui/HUD/statusfx/paralyze.png",
				"sizex": 32,
				"sizey": 32
				}					
			]
        },
        "tutorial8n": {
            "sign": [
				"A veces lanzar una",
				"poción beneficiosa es",
				"la mejor manera de",
				"ayudar a los aliados."
            ],
            "attributes": {
                "font": "fonts/pixelmix.ttf#16#2",
                "horizontal_justify": "center",
                "vertical_justify": "center",
                "line_padding": 0,
                "top_padding": 0,
                "inline_img_adjust_x": 0,
                "word_highlights": [],
                "word_highlights2": [
					[],
					[0],
					[],
					[0,1]
				]
            },
            "variables": []
        },
        "tutorial8o": {
            "sign": [
				"Poción de Curar Dolencia",
				"$",
				"Beber esto elimina la mayoría",
				"de los efectos de estado,",
				"incluidos los positivos."
            ],
            "attributes": {
                "font": "fonts/pixelmix.ttf#16#2",
                "horizontal_justify": "center",
                "vertical_justify": "center",
                "line_padding": 0,
                "top_padding": 0,
                "inline_img_adjust_x": 0,
                "word_highlights": [],
                "word_highlights2": [
					[],
					[],
					[],
					[1,2]
				]
            },
            "variables": [
				{
				"type": "image",
				"value": "*#data/scripts/tutorial8/sign_cure.png",
				"sizex": 0,
				"sizey": 0
				}				
			]
        },
        "tutorial8p": {
            "sign": [
				"Las pociones con efectos",
				"beneficiosos se consumen",
				"como acción predeterminada,",
				"mientras que las pociones",
				"dañinas se equipan para ser",
				"lanzadas con$ ."
            ],
            "attributes": {
                "font": "fonts/pixelmix.ttf#16#2",
                "horizontal_justify": "center",
                "vertical_justify": "center",
                "line_padding": 0,
                "top_padding": 0,
                "inline_img_adjust_x": 0,
                "word_highlights": [
					[],
					[],
					[1,2],
					[],
					[],
					[1]
				],
                "word_highlights2": [
					[],
					[2],
					[],
					[],
					[0]
				],
				"video": {
					"background_img": "data/scripts/video_frame_noalpha.png",
					"background_border": 8,
					"path": "data/scripts/tutorial8/potionoffense_mk.ogv",
					"x": 0,
					"y": 0,
					"w": 0,
					"h": 0
				}
            },
            "variables": [
				{
					"type": "input_glyph",
					"value": "Attack"
				}				
			]
        },
        "tutorial8p_gamepad": {
            "sign": [
				"Las pociones con efectos",
				"beneficiosos se consumen",
				"como acción predeterminada,",
				"mientras que las pociones",
				"dañinas se equipan para ser",
				"lanzadas con$ ."
            ],
            "attributes": {
                "font": "fonts/pixelmix.ttf#16#2",
                "horizontal_justify": "center",
                "vertical_justify": "center",
                "line_padding": 0,
                "top_padding": 0,
                "inline_img_adjust_x": 0,
                "word_highlights": [
					[],
					[],
					[1,2],
					[],
					[],
					[1]
				],
                "word_highlights2": [
					[],
					[2],
					[],
					[],
					[0]
				],
				"video": {
					"background_img": "data/scripts/video_frame_noalpha.png",
					"background_border": 8,
					"path": "data/scripts/tutorial8/potionoffense_gamepad.ogv",
					"x": 0,
					"y": 0,
					"w": 0,
					"h": 0
				}
            },
            "variables": [
				{
					"type": "input_glyph",
					"value": "Attack"
				}				
			]
        },		
        "tutorial8q": {
            "sign": [
				"Las pociones pueden ser",
				"lanzadas o bebidas.",
				"",
				"Si una poción está",
				"identificada, su Hotbar",
				"y el comportamiento base$",
				"ajustarán a su efecto."
            ],
            "attributes": {
                "font": "fonts/pixelmix.ttf#16#2",
                "horizontal_justify": "center",
                "vertical_justify": "center",
                "line_padding": 0,
                "top_padding": 0,
                "inline_img_adjust_x": 0,
                "word_highlights": [
					[],
					[],
					[],
					[],
					[],
					[0,2]
				],
                "word_highlights2": [
					[],
					[0,2],
					[],
					[],
					[0],
					[],
					[],
					[2]
				]
            },
            "variables": [
				{
					"type": "input_glyph",
					"value": "MenuRightClick"
				}			
			]
        },
		"tutorial8q_gamepad": {
            "sign": [
				"Las pociones pueden ser",
				"lanzadas o bebidas.",
				"",
				"Si una poción está",
				"identificada, su Hotbar",
				"y el comportamiento base$",
				"ajustarán a su efecto."
            ],
            "attributes": {
                "font": "fonts/pixelmix.ttf#16#2",
                "horizontal_justify": "center",
                "vertical_justify": "center",
                "line_padding": 0,
                "top_padding": 0,
                "inline_img_adjust_x": 0,
                "word_highlights": [
					[],
					[],
					[],
					[],
					[],
					[0,2]
				],
                "word_highlights2": [
					[],
					[0,2],
					[],
					[],
					[0],
					[],
					[],
					[2]
				]
            },
            "variables": [
				{
					"type": "input_glyph",
					"value": "MenuConfirm"
				}			
			]
        },
        "tutorial8r": {
            "sign": [
				"Estás Envenenado.",
				"",
				"$ ",
				"",
				"Bébelo desde tu",
				"inventario con$ ."
            ],
            "attributes": {
                "font": "fonts/pixelmix.ttf#16#2",
				"font_highlight2_color": {
					"r": 255,
					"g": 64,
					"b": 64,
					"a": 255
					},	
                "horizontal_justify": "center",
                "vertical_justify": "center",
                "line_padding": 0,
                "top_padding": 0,
                "inline_img_adjust_x": 0,
                "word_highlights": [
					[],
					[],
					[],
					[],
					[],
					[1]
				],
                "word_highlights2": [
					[2]
				]
            },
            "variables": [
				{
				"type": "image",
				"value": "*#items/images/spells/cureailment.png",
				"sizex": 32,
				"sizey": 32
				},
				{
					"type": "input_glyph",
					"value": "MenuRightClick"
				}					
			]
        },
		"tutorial8r_gamepad": {
            "sign": [
				"Estás Envenenado.",
				"",
				"$ ",
				"",
				"Bébelo desde tu",
				"inventario con$ ."
            ],
            "attributes": {
                "font": "fonts/pixelmix.ttf#16#2",
				"font_highlight2_color": {
					"r": 255,
					"g": 64,
					"b": 64,
					"a": 255
					},	
                "horizontal_justify": "center",
                "vertical_justify": "center",
                "line_padding": 0,
                "top_padding": 0,
                "inline_img_adjust_x": 0,
                "word_highlights": [
					[],
					[],
					[],
					[],
					[],
					[1]
				],
                "word_highlights2": [
					[2]
				]
            },
            "variables": [
				{
				"type": "image",
				"value": "*#items/images/spells/cureailment.png",
				"sizex": 32,
				"sizey": 32
				},
				{
					"type": "input_glyph",
					"value": "MenuConfirm"
				}					
			]
        },
        "tutorial8s": {
            "sign": [
				"Cada tipo de poción",
				"viene en un cierto",
				"rango de colores,",
				"y puede ser útil",
				"o perjudicial."
            ],
            "attributes": {
                "font": "fonts/pixelmix.ttf#16#2",
                "horizontal_justify": "center",
                "vertical_justify": "center",
                "line_padding": 0,
                "top_padding": 0,
                "inline_img_adjust_x": 0,
                "word_highlights": [],
                "word_highlights2": [
					[],
					[],
					[0,1,2]
				]
            },
            "variables": []
        },
        "tutorial8t": {
            "sign": [
				"Para empuñar pociones beneficiosas",
				"o sin identificar, desde tu hotbar,",
				"mantén$ mientras pulsas la tecla",
				"asignada del hotbar."
            ],
            "attributes": {
                "font": "fonts/pixelmix.ttf#16#2",
                "horizontal_justify": "center",
                "vertical_justify": "center",
                "line_padding": 0,
                "top_padding": 0,
                "inline_img_adjust_x": 0,
                "word_highlights": [
					[1],
					[],
					[],
					[0,1,2]
				],
                "word_highlights2": [
				[],
				[],
				[0,1,2]
				]
            },
            "variables": [
				{
				"type": "image",
				"value": "*#images/ui/Glyphs/KeyboardGlyphs/Rendered/NamedKeys/Unpressed_Text_Alt_00.png",
				"sizex": 0,
				"sizey": 0
				}	
			]
        },
        "tutorial8t_gamepad": {
            "sign": [
				"Para empuñar pociones beneficiosas",
				"o sin identificar, pulsa$ en la,",
				"poción ubicada en tu inventario y ",
				"selecciona [Empuñar] desde el menú",
				"desplegable."
            ],
            "attributes": {
                "font": "fonts/pixelmix.ttf#16#2",
                "horizontal_justify": "center",
                "vertical_justify": "center",
                "line_padding": 0,
                "top_padding": 0,
                "inline_img_adjust_x": 0,
                "word_highlights": [
					[1],
					[],
					[0],
					[],
					[1]
				],
                "word_highlights2": []
            },
            "variables": [
				{
					"type": "input_glyph",
					"value": "MenuConfirm"
				}				
			]
        },	
        "tutorial8u": {
            "sign": [
				"Poción de Enfermedad",
				"",
				"$ ",
				"",
				"Lánzalo a un enemigo",
				"para envenenarlo.",
				"Destruye el maniquí",
				"y procede."
            ],
            "attributes": {
                "font": "fonts/pixelmix.ttf#16#2",
                "horizontal_justify": "center",
                "vertical_justify": "center",
                "line_padding": 0,
                "top_padding": 0,
                "inline_img_adjust_x": 0,
                "word_highlights": [
					[],
					[],
					[],
					[],
					[0]
				],
                "word_highlights2": [
					[],
					[],
					[],
					[],
					[],
					[],
					[0,1,2]
				],
				"video": {
					"background_img": "data/scripts/video_frame_half_noalpha.png",
					"background_border": 8,
					"path": "data/scripts/tutorial8/potionthrow.ogv",
					"x": 0,
					"y": 0,
					"w": 0,
					"h": 0
				}
            },
            "variables": [
				{
				"type": "image",
				"value": "*#images/ui/HUD/statusfx/poisoned.png",
				"sizex": 32,
				"sizey": 32
				}					
			]
        },
        "tutorial8v": {
            "sign": [
				"Usa pociones para que",
				"el centinela logre",
				"derrotar al esqueleto.",
				"El centinela está dañado,",
				"y fracasará sin ninguna",
				"asistencia.",
				"",
				"Tira de la palanca",
				"para comenzar."
            ],
            "attributes": {
                "font": "fonts/pixelmix.ttf#16#2",
				"font_highlight_color": {
					"r": 255,
					"g": 64,
					"b": 64,
					"a": 255
					},					
                "horizontal_justify": "center",
                "vertical_justify": "center",
                "line_padding": 0,
                "top_padding": 0,
                "inline_img_adjust_x": 0,
                "word_highlights": [
					[],
					[],
					[],
					[],
					[1,2]
				],
                "word_highlights2": [
					[],
					[],
					[0,1,2],
					[],
					[],
					[],
					[],
					[0,1,2]
				],
				"video": {
					"background_img": "data/scripts/video_frame_half_noalpha.png",
					"background_border": 8,
					"path": "data/scripts/tutorial8/healsentry.ogv",
					"x": 0,
					"y": 0,
					"w": 0,
					"h": 0
				}
            },
            "variables": []
        },
        "tutorial8w": {
            "sign": [
				"Todas las buenas recetas",
				"tienen un ingrediente base.",
				"Las mezclas incorrectas resultan",
				"en una poción de enfermedad.",
				"",
				"Mezcla jugo de frutas y",
				"alcohol en el alambique",
				"para una receta fallida."
            ],
            "attributes": {
                "font": "fonts/pixelmix.ttf#16#2",
				"font_highlight_color": {
					"r": 255,
					"g": 64,
					"b": 64,
					"a": 255
					},	
                "horizontal_justify": "center",
                "vertical_justify": "center",
                "line_padding": 0,
                "top_padding": 0,
                "inline_img_adjust_x": 0,
                "word_highlights": [
					[],
					[],
					[],
					[1,2,3],
					[],
					[],
					[],
					[2,3]
				],
                "word_highlights2": [
					[],
					[2,3]					
				],
				"video": {
					"background_img": "data/scripts/video_frame_noalpha.png",
					"background_border": 8,
					"path": "data/scripts/tutorial8/sickbrew_mk.ogv",
					"x": 0,
					"y": 0,
					"w": 0,
					"h": 0
				}
            },
            "variables": []
        },
        "tutorial8w_gamepad": {
            "sign": [
				"Todas las buenas recetas",
				"tienen un ingrediente base.",
				"Las mezclas incorrectas resultan",
				"en una poción de enfermedad.",
				"",
				"Mezcla jugo de frutas y",
				"alcohol en el alambique",
				"para una receta fallida."
            ],
            "attributes": {
                "font": "fonts/pixelmix.ttf#16#2",
				"font_highlight_color": {
					"r": 255,
					"g": 64,
					"b": 64,
					"a": 255
					},	
                "horizontal_justify": "center",
                "vertical_justify": "center",
                "line_padding": 0,
                "top_padding": 0,
                "inline_img_adjust_x": 0,
                "word_highlights": [
					[],
					[],
					[],
					[1,2,3],
					[],
					[],
					[],
					[2,3]
				],
                "word_highlights2": [
					[],
					[2,3]					
				],
				"video": {
					"background_img": "data/scripts/video_frame_noalpha.png",
					"background_border": 8,
					"path": "data/scripts/tutorial8/sickbrew_gamepad.ogv",
					"x": 0,
					"y": 0,
					"w": 0,
					"h": 0
				}
            },
            "variables": []
        },		
        "tutorial8x": {
            "sign": [
				"Ácido",
				"$", 
				"Usado para hacer mortales",
				"Pociones Inestables, que",
				"escalarán en potencia junto",
				"con su alquimista."
            ],
            "attributes": {
                "font": "fonts/pixelmix.ttf#16#2",
                "horizontal_justify": "center",
                "vertical_justify": "center",
                "line_padding": 0,
                "top_padding": 0,
                "inline_img_adjust_x": 0,
                "word_highlights": [],
                "word_highlights2": [
					[],
					[],
					[],
					[0,1],
					[0,1,2]
				]
            },
            "variables": [
				{
				"type": "image",
				"value": "*#data/scripts/tutorial8/sign_acid.png",
				"sizex": 0,
				"sizey": 0
				}				
			]
        },
        "tutorial8y": {
            "sign": [
				"En la próxima sala,",
				"encontrarás una",
				"variedad de pociones",
				"para experimentar.",
				"",
				"Cuando hayas creado",
				"una mezcla exitosa, su",
				"receta se agregará al",
				"Registro del Alambique."
            ],
            "attributes": {
                "font": "fonts/pixelmix.ttf#16#2",
                "horizontal_justify": "center",
                "vertical_justify": "center",
                "line_padding": 0,
                "top_padding": 0,
                "inline_img_adjust_x": 0,
                "word_highlights": [
					[],
					[],
					[],
					[],
					[],
					[],
					[],
					[],
					[2,3]
				],
                "word_highlights2": [
					[],
					[],
					[],
					[1],
					[],
					[],
					[1,2]
				]
            },
            "variables": []
        },
        "tutorial8z": {
            "sign": [
				"Los males y bendiciones",
				"ofrecidos por las fuentes",
				"son demasiado tentadores",
				"para la mayoría de las personas.",
				"Especialmente para quienes",
				"anhelan pociones."
            ],
            "attributes": {
                "font": "fonts/pixelmix.ttf#16#2",
				"font_highlight_color": {
					"r": 255,
					"g": 64,
					"b": 64,
					"a": 255
					},	
                "horizontal_justify": "center",
                "vertical_justify": "center",
                "line_padding": 0,
                "top_padding": 0,
                "inline_img_adjust_x": 0,
                "word_highlights": [
					[1]
				],
                "word_highlights2": [
					[3],
					[],
					[],
					[],
					[],
					[1,2]
				],
				"video": {
					"background_img": "data/scripts/video_frame_noalpha.png",
					"background_border": 8,
					"path": "data/scripts/tutorial8/fountains.ogv",
					"x": 0,
					"y": 0,
					"w": 0,
					"h": 0
				}
            },
            "variables": []
        },
        "tutorial8ab": {
            "sign": [
				"Poción de Restaurar Magia",
				"$",
				"Útil para lanzadores de hechizos.",
				"Mezclar con Jugo de Frutas para",
				"crear Pociones de Curación."
            ],
            "attributes": {
                "font": "fonts/pixelmix.ttf#16#2",
                "horizontal_justify": "center",
                "vertical_justify": "center",
                "line_padding": 0,
                "top_padding": 0,
                "inline_img_adjust_x": 0,
                "word_highlights": [],
                "word_highlights2": [
					[],
					[],
					[2],
					[],
					[1,2,3]
				]
            },
            "variables": [
				{
				"type": "image",
				"value": "*#data/scripts/tutorial5/sign_restoremp.png",
				"sizex": 0,
				"sizey": 0
				}					
			]
        },
        "tutorial8ac": {
            "sign": [
				"Poción de Ceguera",
				"",
				"$",
				"",
				"Quienes la padecen tienen",
				"dificultades para ver.",
				"Mezclar con Jugo de Frutas",
				"para completar la receta de",
				"Curar Dolencia."
            ],
            "attributes": {
                "font": "fonts/pixelmix.ttf#16#2",
                "horizontal_justify": "center",
                "vertical_justify": "center",
                "line_padding": 0,
                "top_padding": 0,
                "inline_img_adjust_x": 0,
                "word_highlights": [],				
                "word_highlights2": [
					[],
					[],
					[],
					[],
					[],
					[],
					[],
					[],
					[0,1]
				]
            },
            "variables": [
				{
				"type": "image",
				"value": "*#images/ui/HUD/statusfx/blind.png",
				"sizex": 32,
				"sizey": 32
				}	
			]
        },
        "tutorial8ad": {
            "sign": [
				"Poción de Confusión",
				"$ ",
				"Mezclar Alcohol con",
				"Pociones de Confusión",
				"para obtener más Ácido.",
				"",
				"La confusión también convierte",
				"Jugo de Frutas en Alcohol",
				"y Ácido en Jugo de Frutas."
            ],
            "attributes": {
                "font": "fonts/pixelmix.ttf#16#2",
                "horizontal_justify": "center",
                "vertical_justify": "center",
                "line_padding": 0,
                "top_padding": 0,
                "inline_img_adjust_x": 0,
                "word_highlights": [],
                "word_highlights2": [
					[],
					[],
					[],
					[0,1,2],
					[],
					[],
					[],
					[3],
					[3,4]
				]
            },
            "variables": [
				{
				"type": "image",
				"value": "*#items/images/spells/confuse.png",
				"sizex": 32,
				"sizey": 32
				}			
			]
        },
        "tutorial8ae": {
            "sign": [
				"Poción de Invisibilidad",
				"",
				"$",
				"",
				"Concede invisibilidad.",
				"Mezclar con Restaurar Magia",
				"para crear potentes",
				"pociones de Gran Curación."
            ],
            "attributes": {
                "font": "fonts/pixelmix.ttf#16#2",
                "horizontal_justify": "center",
                "vertical_justify": "center",
                "line_padding": 0,
                "top_padding": 0,
                "inline_img_adjust_x": 0,
                "word_highlights": [],
                "word_highlights2": [
					[],
					[],
					[],
					[],
					[],
					[],
					[],
					[2,3]
				]
            },
            "variables": [
				{
				"type": "image",
				"value": "*#items/images/spells/invisible.png",
				"sizex": 32,
				"sizey": 32
				}				
			]
        },
        "tutorial8af": {
            "sign": [
				"La alquimia puede",
				"ser exigente con",
				"tu inventario.",
				"",
				"Mantén$ y pulsa$ sobre",
				"los objetos del inventario",
				"para soltarlos rápidamente.",
				"Ordena automáticamente con$ ."
            ],
            "attributes": {
                "font": "fonts/pixelmix.ttf#16#2",
                "horizontal_justify": "center",
                "vertical_justify": "center",
                "line_padding": 0,
                "top_padding": 0,
                "inline_img_adjust_x": 0,
                "word_highlights": [
					[],
					[],
					[],
					[],
					[0,2],
					[],
					[0,1,2]
				],
                "word_highlights2": [
					[],
					[],
					[0,1]
				]
            },
            "variables": [
				{
				"type": "image",
				"value": "*#images/ui/Glyphs/KeyboardGlyphs/Rendered/NamedKeys/Unpressed_Text_Shift_00.png",
				"sizex": 0,
				"sizey": 0
				},
				{
					"type": "input_glyph",
					"value": "Attack"
				},
				{
					"type": "input_glyph",
					"value": "Autosort Inventory"
				}						
			]
        },
        "tutorial8af_gamepad": {
            "sign": [
				"La alquimia puede",
				"ser demandante con",
				"tu inventario.",
				"",
				"Remueve objetos que no",
				"necesites del inventario con$ ,",
				"y ordena automáticamente con$ ."
            ],
            "attributes": {
                "font": "fonts/pixelmix.ttf#16#2",
                "horizontal_justify": "center",
                "vertical_justify": "center",
                "line_padding": 0,
                "top_padding": 0,
                "inline_img_adjust_x": 0,
                "word_highlights": [
					[],
					[],
					[],
					[],
					[],
					[3],
					[1,2]
				],
                "word_highlights2": [
					[],
					[],
					[0,1]
				]
            },
            "variables": [
				{
					"type": "input_glyph",
					"value": "MenuAlt2"
				},
				{
					"type": "input_glyph",
					"value": "Autosort Inventory"
				}						
			]
        },		
        "tutorial8ag": {
            "sign": [
				"$",
				"Beber o mezclar",
				"pociones puede",
				"ocasionalmente dar",
				"como resultado una",
				"botella vacía, que",
				"que cualquier alquimista",
				"puede reutilizar."
            ],
            "attributes": {
                "font": "fonts/pixelmix.ttf#16#2",
                "horizontal_justify": "center",
                "vertical_justify": "center",
                "line_padding": 0,
                "top_padding": 0,
                "inline_img_adjust_x": 0,
                "word_highlights": [],
                "word_highlights2": [
					[],
					[],
					[],
					[],
					[1,2]
				]
            },
            "variables": [
				{
				"type": "image",
				"value": "*#data/scripts/tutorial8/sign_bottle.png",
				"sizex": 0,
				"sizey": 0
				}					
			]
        },
        "tutorial8ah": {
            "sign": [
				"Beber o recibir un golpe por",
				"una botella de Alcohol arrojada",
				"causa ebriedad.",
				"",
				"$",
				"",
				"La ebriedad afecta tus",
				"estadísticas y hace que tu",
				"puntería falle por un tiempo."
            ],
            "attributes": {
                "font": "fonts/pixelmix.ttf#16#2",
				"font_highlight_color": {
					"r": 255,
					"g": 64,
					"b": 64,
					"a": 255
					},	
                "horizontal_justify": "center",
                "vertical_justify": "center",
                "line_padding": 0,
                "top_padding": 0,
                "inline_img_adjust_x": 0,
                "word_highlights": [
					[],
					[],
					[],
					[],
					[],
					[],
					[],
					[],
					[1]
				],
                "word_highlights2": [
					[],
					[],
					[1],
					[],
					[],
					[],
					[],
					[0]
				]
            },
            "variables": [
				{
				"type": "image",
				"value": "*#images/system/drunk.png",
				"sizex": 0,
				"sizey": 0
				}				
			]
        },
        "tutorial8ai": {
            "sign": [
				"Las botellas de Alcohol",
				"y Jugo de Frutas no",
				"suelen curar tanto como",
				"las Pociones de Curación,",
				"pero son más comunes."
            ],
            "attributes": {
                "font": "fonts/pixelmix.ttf#16#2",
                "horizontal_justify": "center",
                "vertical_justify": "center",
                "line_padding": 0,
                "top_padding": 0,
                "inline_img_adjust_x": 0,
                "word_highlights": [],
                "word_highlights2": [
					[2],
					[1,2],
					[],
					[],
					[],
					[0,1]
				]
            },
            "variables": []
        },
        "tutorial8aj": {
            "sign": [
                "Bottled Water",
				"$",
				"Mix water with other",
				"potions to duplicate them.",
				"Can reduce hunger a little.",
				"Blessed water is deadly",
				"to certain monsters."
            ],
            "attributes": {
                "font": "fonts/pixelmix.ttf#16#2",
                "horizontal_justify": "center",
                "vertical_justify": "center",
                "line_padding": 0,
                "top_padding": 0,
                "inline_img_adjust_x": 0,
                "word_highlights": [],
                "word_highlights2": [
					[],
					[],
					[],
					[2],
					[],
					[],
					[1,2]
				],
				"video": {
					"background_img": "data/scripts/video_frame_noalpha.png",
					"background_border": 8,
					"path": "data/scripts/tutorial8/duplicate_mk.ogv",
					"x": 0,
					"y": 0,
					"w": 0,
					"h": 0
				}
            },
            "variables": [
				{
				"type": "image",
				"value": "*#data/scripts/tutorial8/sign_water.png",
				"sizex": 0,
				"sizey": 0
				}					
			]
        },
        "tutorial8aj_gamepad": {
            "sign": [
				"Botella de Agua",
				"$",
				"Mezcla agua con otras",
				"pociones para duplicarlas.",
				"Puede reducir un poco el hambre.",
				"El agua bendita es mortal",
				"contra ciertos monstruos."
            ],
            "attributes": {
                "font": "fonts/pixelmix.ttf#16#2",
                "horizontal_justify": "center",
                "vertical_justify": "center",
                "line_padding": 0,
                "top_padding": 0,
                "inline_img_adjust_x": 0,
                "word_highlights": [],
                "word_highlights2": [
					[],
					[],
					[],
					[2],
					[],
					[],
					[1,2]
				],
				"video": {
					"background_img": "data/scripts/video_frame_noalpha.png",
					"background_border": 8,
					"path": "data/scripts/tutorial8/duplicate_gamepad.ogv",
					"x": 0,
					"y": 0,
					"w": 0,
					"h": 0
				}
            },
            "variables": [
				{
				"type": "image",
				"value": "*#data/scripts/tutorial8/sign_water.png",
				"sizex": 0,
				"sizey": 0
				}					
			]
        },		
        "tutorial8ak": {
            "sign": [
				"$",
				"Prepara una Poción de Velocidad",
				"combinando Alcohol con una",
				"Poción de Curar Afección."
            ],
            "attributes": {
                "font": "fonts/pixelmix.ttf#16#2",
                "horizontal_justify": "center",
                "vertical_justify": "center",
                "line_padding": 0,
                "top_padding": 0,
                "inline_img_adjust_x": 0,
                "word_highlights": [],
                "word_highlights2": [
					[],
					[2,3,4]
				]
            },
            "variables": [
				{
				"type": "image",
				"value": "*#items/images/spells/speed.png",
				"sizex": 32,
				"sizey": 32
				}				
			]
        },
        "tutorial8al": {
            "sign": [
				"$ ",
				"Prepara una",
				"Poción de Levitación",
				"mezclando pociones de", 
				"Curar Dolencia con",
				"Invisibilidad."
            ],
            "attributes": {
                "font": "fonts/pixelmix.ttf#16#2",
                "horizontal_justify": "center",
                "vertical_justify": "center",
                "line_padding": 0,
                "top_padding": 0,
                "inline_img_adjust_x": 0,
                "word_highlights": [],
                "word_highlights2": [
					[],
					[],
					[0,1,2]
				]
            },
            "variables": [
				{
				"type": "image",
				"value": "*#items/images/spells/levitation.png",
				"sizex": 32,
				"sizey": 32
				}					
			]
        },
        "tutorial8am": {
            "sign": [
				"$ ",
				"",
                "Potions of Thunderstorm",
                "can be reliably brewed",
				"by mixing Acid and Speed",
				"potions together."
            ],
            "attributes": {
                "font": "fonts/pixelmix.ttf#16#2",
                "horizontal_justify": "center",
                "vertical_justify": "center",
                "line_padding": 0,
                "top_padding": 0,
                "inline_img_adjust_x": 0,
                "word_highlights": [],
                "word_highlights2": [
					[],
					[],
					[0,1,2],
					[],
					[2,4]
				],
				"video": {
					"background_img": "data/scripts/video_frame_noalpha.png",
					"background_border": 8,
					"path": "data/scripts/tutorial8/thunderstorm_mk.ogv",
					"x": 0,
					"y": 0,
					"w": 0,
					"h": 0
				}
            },
            "variables": [
				{
				"type": "image",
				"value": "*#items/images/spells/stoneblood.png",
				"sizex": 32,
				"sizey": 32
				}					
			]
        },
        "tutorial8am_gamepad": {
            "sign": [
				"$ ",
				"",
				"Las Pociones de Tempestad",
				"se pueden preparar de manera",
				"confiable mezclando pociones de",
				"Ácido con de Velocidad."
            ],
            "attributes": {
                "font": "fonts/pixelmix.ttf#16#2",
                "horizontal_justify": "center",
                "vertical_justify": "center",
                "line_padding": 0,
                "top_padding": 0,
                "inline_img_adjust_x": 0,
                "word_highlights": [],
                "word_highlights2": [
					[],
					[],
					[0,1,2],
					[],
					[2,4]
				],
				"video": {
					"background_img": "data/scripts/video_frame_noalpha.png",
					"background_border": 8,
					"path": "data/scripts/tutorial8/thunderstorm_gamepad.ogv",
					"x": 0,
					"y": 0,
					"w": 0,
					"h": 0
				}
            },
            "variables": [
				{
				"type": "image",
				"value": "*#items/images/spells/stoneblood.png",
				"sizex": 32,
				"sizey": 32
				}					
			]
        },		
        "tutorial8pm": {
            "sign": [
				"PRECAUCIÓN:",
				"Una receta incorrecta",
				"usando Ácido resultará",
				"en una letal explosión.",
				"$ ",
				"Si buscas aprender",
				"recetas más poderosas",
				"usando ácido, prepara",
				"curaciones y sanaciones."
            ],
            "attributes": {
                "font": "fonts/pixelmix.ttf#16#2",
				"font_highlight_color": {
					"r": 255,
					"g": 64,
					"b": 64,
					"a": 255
					},	
                "horizontal_justify": "center",
                "vertical_justify": "center",
                "line_padding": 0,
                "top_padding": 0,
                "inline_img_adjust_x": 0,
                "word_highlights": [
					[0],
					[],
					[],
					[2,3]
				],
                "word_highlights2": [
					[],
					[1],
					[],
					[],
					[],
					[],
					[1,2],
					[],
					[0,2]
				],
				"video": {
					"background_img": "data/scripts/video_frame_noalpha.png",
					"background_border": 8,
					"path": "data/scripts/tutorial8/splode_mk.ogv",
					"x": 0,
					"y": 0,
					"w": 0,
					"h": 0
				}
            },
            "variables": [
				{
				"type": "image",
				"value": "*#images/ui/HUD/statusfx/burning.png",
				"sizex": 32,
				"sizey": 32
				}					
			]
        },
        "tutorial8pm_gamepad": {
            "sign": [
				"PRECAUCIÓN:",
				"Una receta incorrecta",
				"usando Ácido resultará",
				"en una letal explosión.",
				"$ ",
				"Si buscas aprender",
				"recetas más poderosas",
				"usando ácido, prepara",
				"curaciones y sanaciones."
            ],
            "attributes": {
                "font": "fonts/pixelmix.ttf#16#2",
				"font_highlight_color": {
					"r": 255,
					"g": 64,
					"b": 64,
					"a": 255
					},	
                "horizontal_justify": "center",
                "vertical_justify": "center",
                "line_padding": 0,
                "top_padding": 0,
                "inline_img_adjust_x": 0,
                "word_highlights": [
					[0],
					[],
					[],
					[2,3]
				],
                "word_highlights2": [
					[],
					[1],
					[],
					[],
					[],
					[],
					[1,2],
					[],
					[0,2]
				],
				"video": {
					"background_img": "data/scripts/video_frame_noalpha.png",
					"background_border": 8,
					"path": "data/scripts/tutorial8/splode_gamepad.ogv",
					"x": 0,
					"y": 0,
					"w": 0,
					"h": 0
				}
            },
            "variables": [
				{
				"type": "image",
				"value": "*#images/ui/HUD/statusfx/burning.png",
				"sizex": 32,
				"sizey": 32
				}					
			]
        },			
        "tutorial8an": {
            "sign": [
				"PRECAUCIÓN:",
				"Los monstruos son conocidos",
				"por infestar las tuberías.",
				"",
				"Asegúrate de prepararte para",
				"defenderte antes de intentar",
				"beber o usar fuentes de agua."
            ],
            "attributes": {
                "font": "fonts/pixelmix.ttf#16#2",
				"font_highlight_color": {
					"r": 255,
					"g": 64,
					"b": 64,
					"a": 255
					},					
                "horizontal_justify": "center",
                "vertical_justify": "center",
                "line_padding": 0,
                "top_padding": 0,
                "inline_img_adjust_x": 0,
                "word_highlights": [
					[0],
					[],
					[1]
				],
                "word_highlights2": [
					[],
					[],
					[],
					[],
					[3],
					[],
					[2],
					[1]
				],
				"video": {
					"background_img": "data/scripts/video_frame_half_noalpha.png",
					"background_border": 8,
					"path": "data/scripts/tutorial8/watermonsters.ogv",
					"x": 0,
					"y": 0,
					"w": 0,
					"h": 0
				}
            },
            "variables": []
        },
        "tutorial8ao": {
            "sign": [
				"Equipa botellas vacías",
				"para tomar agua de fregaderos",
				"o fuentes usando$ .",
				"",
				"Esto llenará tu",
				"botella con agua",
				"u otras pociones."
            ],
            "attributes": {
                "font": "fonts/pixelmix.ttf#16#2",
                "horizontal_justify": "center",
                "vertical_justify": "center",
                "line_padding": 0,
                "top_padding": 0,
                "inline_img_adjust_x": 0,
                "word_highlights": [
					[0],
					[],
					[1]
				],
                "word_highlights2": [
					[],
					[1],
					[],
					[],
					[2]
				],
				"video": {
					"background_img": "data/scripts/video_frame_noalpha.png",
					"background_border": 8,
					"path": "data/scripts/tutorial8/tap_mk.ogv",
					"x": 0,
					"y": 0,
					"w": 0,
					"h": 0
				}
            },
            "variables": [
				{
					"type": "input_glyph",
					"value": "Attack"
				}			
			]
        },
        "tutorial8ao_gamepad": {
            "sign": [
				"Equipa botellas vacías",
				"para tomar agua de fregaderos",
				"o fuentes usando$ .",
				"",
				"Esto llenará tu",
				"botella con agua",
				"u otras pociones."
            ],
            "attributes": {
                "font": "fonts/pixelmix.ttf#16#2",
                "horizontal_justify": "center",
                "vertical_justify": "center",
                "line_padding": 0,
                "top_padding": 0,
                "inline_img_adjust_x": 0,
                "word_highlights": [
					[0],
					[],
					[1]
				],
                "word_highlights2": [
					[],
					[1],
					[],
					[],
					[2]
				],
				"video": {
					"background_img": "data/scripts/video_frame_noalpha.png",
					"background_border": 8,
					"path": "data/scripts/tutorial8/tap_gamepad.ogv",
					"x": 0,
					"y": 0,
					"w": 0,
					"h": 0
				}
            },
            "variables": [
				{
					"type": "input_glyph",
					"value": "Attack"
				}			
			]
        },
        "tutorial8aw": {
            "sign": [
				"El agua de la mazmorra es muy",
				"impura para elaborar pociones.",
				"Los alquimistas deben confiar en",
				"bombas de agua fresca, comercios,",
				"o fuentes para abastecerse."
            ],
            "attributes": {
                "font": "fonts/pixelmix.ttf#16#2",
					"font_highlight_color": {
					"r": 255,
					"g": 64,
					"b": 64,
					"a": 255
					},	
                "horizontal_justify": "center",
                "vertical_justify": "center",
                "line_padding": 0,
                "top_padding": 0,
                "inline_img_adjust_x": 0,
                "word_highlights": [
					[],
					[0,1,2]
				],
                "word_highlights2": [
					[],
					[],
					[],
					[0,1,2,3],
					[1]
				]
            },
            "variables": []
        },		
        "tutorial8az": {
            "sign": [
				"Decantar:",
				"",
				"Mezclar dos pociones",
				"con el mismo efecto",
				"en un solo tipo de",
				"botella, permitiendo",
				"que se organicen en",
				"una sola."
            ],
            "attributes": {
                "font": "fonts/pixelmix.ttf#16#2",
                "horizontal_justify": "center",
                "vertical_justify": "center",
                "line_padding": 0,
                "top_padding": 0,
                "inline_img_adjust_x": 0,
                "word_highlights": [
					[0]
				],
                "word_highlights2": [
					[],
					[],
					[],
					[],
					[],
					[],
					[],
					[0]
				],
				"video": {
					"background_img": "data/scripts/video_frame_noalpha.png",
					"background_border": 8,
					"path": "data/scripts/tutorial8/decanting_mk.ogv",
					"x": 0,
					"y": 0,
					"w": 0,
					"h": 0
				}
            },
            "variables": []
        },
        "tutorial8az_gamepad": {
            "sign": [
				"Decantar:",
				"",
				"Mezclar dos pociones",
				"con el mismo efecto",
				"en un solo tipo de",
				"botella, permitiendo",
				"que se organicen en",
				"una sola."
            ],
            "attributes": {
                "font": "fonts/pixelmix.ttf#16#2",
                "horizontal_justify": "center",
                "vertical_justify": "center",
                "line_padding": 0,
                "top_padding": 0,
                "inline_img_adjust_x": 0,
                "word_highlights": [
					[0]
				],
                "word_highlights2": [
					[],
					[],
					[],
					[],
					[],
					[],
					[],
					[0]
				],
				"video": {
					"background_img": "data/scripts/video_frame_noalpha.png",
					"background_border": 8,
					"path": "data/scripts/tutorial8/decanting_gamepad.ogv",
					"x": 0,
					"y": 0,
					"w": 0,
					"h": 0
				}
            },
            "variables": []
        }				
    }
}